molgx/DataBox.py
molgx/FeatureEstimation.py
molgx/FeatureExtraction.py
molgx/Generation.py
molgx/Molecule.py
molgx/Prediction.py
molgx/Utility.py
molgx/__init__.py
molgx/molgxsdk.py
molgx/ChemGenerator/ChemGraph.py
molgx/ChemGenerator/ChemGraphFragment.py
molgx/ChemGenerator/ChemGraphGen.py
molgx/ChemGenerator/ChemGraphGenPath.py
molgx/ChemGenerator/ChemGraphLabeling.py
molgx/ChemGenerator/ChemGraphResource.py
molgx/ChemGenerator/ChemGraphUtil.py
molgx/ChemGenerator/ChemRingGen.py
molgx/ChemGenerator/__init__.py
molgx/config/default_rings.csv
molgx-0.22.0a1.dist-info/AUTHORS
molgx-0.22.0a1.dist-info/LICENSE
molgx-0.22.0a1.dist-info/METADATA
molgx-0.22.0a1.dist-info/WHEEL
molgx-0.22.0a1.dist-info/top_level.txt
molgx-0.22.0a1.dist-info/RECORD
