Metadata-Version: 2.1
Name: molgx
Version: 0.22.0a1
Summary: Package for Molecule Generation Experience (MolGX).
Author: MolGX team
License: MIT
Keywords: MolGX Generative Models Inference Training
Classifier: Operating System :: OS Independent
Classifier: Programming Language :: Python :: 3
Classifier: Programming Language :: Python :: 3.7
License-File: LICENSE
License-File: AUTHORS
Requires-Dist: ipython
Requires-Dist: matplotlib
Requires-Dist: numpy
Requires-Dist: pandas
Requires-Dist: rdkit-pypi
Requires-Dist: scikit-learn
Requires-Dist: scipy
